VeloxEngine/VeloxEngine.py
VeloxEngine/__init__.py
veloxengine-0.1.2.dist-info/METADATA
veloxengine-0.1.2.dist-info/WHEEL
veloxengine-0.1.2.dist-info/top_level.txt
veloxengine-0.1.2.dist-info/RECORD
