Metadata-Version: 2.1
Name: VeloxEngine
Version: 0.1.2
Summary: A minimal SDL2-based game engine in Python for building 2D games quickly.
Home-page: https://pixnox-studio.github.io/Velox-Web/
Author: AynuDaDev
Classifier: Programming Language :: Python :: 3
Classifier: License :: OSI Approved :: MIT License
Classifier: Operating System :: OS Independent
Requires-Python: >=3.7
Requires-Dist: PySDL2
